uklookup/__init__.py
uklookup/postcodes.py
uklookup/trim.py
uklookup/version.py
uklookup/codepointopen/Data/CSV/ab.csv.gz
uklookup/codepointopen/Data/CSV/al.csv.gz
uklookup/codepointopen/Data/CSV/b.csv.gz
uklookup/codepointopen/Data/CSV/ba.csv.gz
uklookup/codepointopen/Data/CSV/bb.csv.gz
uklookup/codepointopen/Data/CSV/bd.csv.gz
uklookup/codepointopen/Data/CSV/bh.csv.gz
uklookup/codepointopen/Data/CSV/bl.csv.gz
uklookup/codepointopen/Data/CSV/bn.csv.gz
uklookup/codepointopen/Data/CSV/br.csv.gz
uklookup/codepointopen/Data/CSV/bs.csv.gz
uklookup/codepointopen/Data/CSV/ca.csv.gz
uklookup/codepointopen/Data/CSV/cb.csv.gz
uklookup/codepointopen/Data/CSV/cf.csv.gz
uklookup/codepointopen/Data/CSV/ch.csv.gz
uklookup/codepointopen/Data/CSV/cm.csv.gz
uklookup/codepointopen/Data/CSV/co.csv.gz
uklookup/codepointopen/Data/CSV/cr.csv.gz
uklookup/codepointopen/Data/CSV/ct.csv.gz
uklookup/codepointopen/Data/CSV/cv.csv.gz
uklookup/codepointopen/Data/CSV/cw.csv.gz
uklookup/codepointopen/Data/CSV/da.csv.gz
uklookup/codepointopen/Data/CSV/dd.csv.gz
uklookup/codepointopen/Data/CSV/de.csv.gz
uklookup/codepointopen/Data/CSV/dg.csv.gz
uklookup/codepointopen/Data/CSV/dh.csv.gz
uklookup/codepointopen/Data/CSV/dl.csv.gz
uklookup/codepointopen/Data/CSV/dn.csv.gz
uklookup/codepointopen/Data/CSV/dt.csv.gz
uklookup/codepointopen/Data/CSV/dy.csv.gz
uklookup/codepointopen/Data/CSV/e.csv.gz
uklookup/codepointopen/Data/CSV/ec.csv.gz
uklookup/codepointopen/Data/CSV/eh.csv.gz
uklookup/codepointopen/Data/CSV/en.csv.gz
uklookup/codepointopen/Data/CSV/ex.csv.gz
uklookup/codepointopen/Data/CSV/fk.csv.gz
uklookup/codepointopen/Data/CSV/fy.csv.gz
uklookup/codepointopen/Data/CSV/g.csv.gz
uklookup/codepointopen/Data/CSV/gl.csv.gz
uklookup/codepointopen/Data/CSV/gu.csv.gz
uklookup/codepointopen/Data/CSV/ha.csv.gz
uklookup/codepointopen/Data/CSV/hd.csv.gz
uklookup/codepointopen/Data/CSV/hg.csv.gz
uklookup/codepointopen/Data/CSV/hp.csv.gz
uklookup/codepointopen/Data/CSV/hr.csv.gz
uklookup-0.0.4.dist-info/METADATA
uklookup-0.0.4.dist-info/WHEEL
uklookup-0.0.4.dist-info/entry_points.txt
uklookup-0.0.4.dist-info/top_level.txt
uklookup-0.0.4.dist-info/RECORD
