Metadata-Version: 2.4
Name: uklookup
Version: 0.0.4
Summary: A tool to look up UK postcode eastings, northings, and convert them to latitude and longitude.
Home-page: https://github.com/hugohadfield/uklookup
Author: Hugo Hadfield
Author-email: hadfield.hugo@gmail.com
License: MIT
Classifier: Programming Language :: Python :: 3
Classifier: License :: OSI Approved :: MIT License
Classifier: Operating System :: OS Independent
Requires-Python: >=3.6
Requires-Dist: numpy
Requires-Dist: convertbng
Dynamic: author
Dynamic: author-email
Dynamic: classifier
Dynamic: description
Dynamic: description-content-type
Dynamic: home-page
Dynamic: license
Dynamic: requires-dist
Dynamic: requires-python
Dynamic: summary
